LICENSE
README.md
pyproject.toml
docs/developers/README.md
docs/original/docker/README.md
docs/original/library/README.md
docs/scenario_configs/README.md
docs/slides/README.md
armory/__init__.py
armory/environment.py
armory/logs.py
armory/version.py
armory/art_experimental/__init__.py
armory/art_experimental/attacks/__init__.py
armory/art_experimental/attacks/carla_adversarial_texture.py
armory/art_experimental/attacks/carla_mot_adversarial_patch.py
armory/art_experimental/attacks/carla_mot_patch.py
armory/art_experimental/attacks/carla_obj_det_adversarial_patch.py
armory/art_experimental/attacks/carla_obj_det_patch.py
armory/art_experimental/attacks/carla_obj_det_utils.py
armory/art_experimental/attacks/cascading_attack.py
armory/art_experimental/attacks/dapricot_patch.py
armory/art_experimental/attacks/fgm_binary_search.py
armory/art_experimental/attacks/frame.py
armory/art_experimental/attacks/gradient_matching.py
armory/art_experimental/attacks/kenansville_dft.py
armory/art_experimental/attacks/patch.py
armory/art_experimental/attacks/pgd_patch.py
armory/art_experimental/attacks/poison_loader_audio.py
armory/art_experimental/attacks/poison_loader_clbd.py
armory/art_experimental/attacks/poison_loader_dlbd.py
armory/art_experimental/attacks/robust_dpatch.py
armory/art_experimental/attacks/snr_pgd.py
armory/art_experimental/attacks/sweep.py
armory/art_experimental/attacks/video_frame_border.py
armory/art_experimental/defences/__init__.py
armory/art_experimental/defences/base.py
armory/art_experimental/defences/jpeg_compression_multichannel_image.py
armory/art_experimental/defences/jpeg_compression_normalized.py
armory/art_experimental/defences/random_affine_pytorch.py
armory/art_experimental/defences/transformer.py
armory/art_experimental/defences/video_compression_normalized.py
armory/art_experimental/poison_detection/__init__.py
armory/art_experimental/poison_detection/random_filter.py
armory/attacks/__init__.py
armory/attacks/librispeech_target_labels.py
charmory-23.9.dist-info/METADATA
charmory-23.9.dist-info/WHEEL
charmory-23.9.dist-info/entry_points.txt
charmory-23.9.dist-info/licenses/LICENSE
charmory-23.9.dist-info/RECORD
