Metadata-Version: 2.1
Name: charmory
Version: 23.9
Summary: Adversarial Robustness Evaluation Library
Project-URL: Homepage, https://github.com/twosixlabs/armory
Project-URL: BugTracker, https://github.com/twosixlabs/armory/issues
Project-URL: Documentation, https://armory.readthedocs.io/en/latest/
Author-email: Two Six Technologies <armory@twosixtech.com>
License-Expression: MIT
License-File: LICENSE
Classifier: Development Status :: 4 - Beta
Classifier: License :: OSI Approved :: MIT License
Classifier: Programming Language :: Python :: 3
Classifier: Topic :: Scientific/Engineering :: Artificial Intelligence
Requires-Python: >=3.8
Requires-Dist: adversarial-robustness-toolbox==1.15.1
Requires-Dist: boto3
Requires-Dist: botocore
Requires-Dist: ffmpeg-python
Requires-Dist: lightning
Requires-Dist: loguru
Requires-Dist: matplotlib
Requires-Dist: mlflow
Requires-Dist: numpy
Requires-Dist: opencv-python-headless==4.5.5.62
Requires-Dist: opencv-python==4.5.5.62
Requires-Dist: pandas
Requires-Dist: pillow
Requires-Dist: pydub
Requires-Dist: requests
Requires-Dist: scikit-learn<1.2.0
Requires-Dist: scipy
Requires-Dist: setuptools-scm
Requires-Dist: tensorboardx
Requires-Dist: tensorflow>=2.11.0
Requires-Dist: tf-models-official
Requires-Dist: tidecv
Requires-Dist: torch>=2.0.0
Requires-Dist: torchaudio>=2.0.1
Requires-Dist: torchvision>=0.15.1
Requires-Dist: transformers
Provides-Extra: all
Requires-Dist: charmory[developer]; extra == 'all'
Requires-Dist: charmory[documentation]; extra == 'all'
Provides-Extra: developer
Requires-Dist: bandit[toml]; extra == 'developer'
Requires-Dist: black[jupyter]; extra == 'developer'
Requires-Dist: flake8; extra == 'developer'
Requires-Dist: hatch; extra == 'developer'
Requires-Dist: ipywidgets; extra == 'developer'
Requires-Dist: isort; extra == 'developer'
Requires-Dist: pre-commit; extra == 'developer'
Requires-Dist: pytest; extra == 'developer'
Requires-Dist: wheel; extra == 'developer'
Provides-Extra: documentation
Requires-Dist: mkdocs; extra == 'documentation'
Requires-Dist: mkdocs-exclude; extra == 'documentation'
Requires-Dist: mkdocs-material; extra == 'documentation'
Requires-Dist: mkdocstrings; extra == 'documentation'
Provides-Extra: extras
Requires-Dist: apache-beam>=2.22.0; extra == 'extras'
Requires-Dist: google-cloud-storage; extra == 'extras'
Requires-Dist: librosa; extra == 'extras'
Requires-Dist: protobuf; extra == 'extras'
Requires-Dist: python-levenshtein; extra == 'extras'
Requires-Dist: sox; extra == 'extras'
Requires-Dist: tensorflow-datasets!=4.9.0,>=4.6.0; extra == 'extras'
Requires-Dist: torchmetrics<0.8.0; extra == 'extras'
Requires-Dist: transformers; extra == 'extras'
